statecraft/__init__.py
statecraft/_setup.py
statecraft/cache.py
statecraft/client.py
statecraft/core.py
statecraft/metadata.py
statecraft/models.py
statecraft/states_list.py
statecraft/user_attributes.py
statecraft/utils.py
statecraft-0.3.0.dist-info/LICENSE
statecraft-0.3.0.dist-info/METADATA
statecraft-0.3.0.dist-info/WHEEL
statecraft-0.3.0.dist-info/RECORD
