Metadata-Version: 2.1
Name: statecraft
Version: 0.3.0
Summary: Store, manage and remix states for SSMs and other Stateful models
License: Apache-2.0
Author: koayon
Author-email: koayon@gmail.com
Requires-Python: >=3.8,<4.0
Classifier: Development Status :: 4 - Beta
Classifier: Intended Audience :: Developers
Classifier: License :: OSI Approved :: Apache Software License
Classifier: License :: OSI Approved :: MIT License
Classifier: Operating System :: OS Independent
Classifier: Programming Language :: Python :: 3
Classifier: Programming Language :: Python :: 3.8
Classifier: Programming Language :: Python :: 3.9
Classifier: Programming Language :: Python :: 3.10
Classifier: Programming Language :: Python :: 3.11
Classifier: Programming Language :: Python :: 3
Classifier: Typing :: Typed
Requires-Dist: Requests (>=2.31.0,<3.0.0)
Requires-Dist: accelerate (>=0.29.1,<0.30.0)
Requires-Dist: einops (>=0.6.1,<0.7.0)
Requires-Dist: pydantic (>=2.5.3,<3.0.0)
Requires-Dist: python-dotenv (>=0.19.1,<0.20.0)
Requires-Dist: torch (>=2.2.2,<3.0.0)
Requires-Dist: transformers (>=4.39.3,<5.0.0)
Requires-Dist: typer (>=0.7.0,<0.8.0)
Project-URL: Repository, https://github.com/koayon/statecraft.git
